samsung_mdc/__init__.py
samsung_mdc/__main__.py
samsung_mdc/cli.py
samsung_mdc/command.py
samsung_mdc/commands.py
samsung_mdc/connection.py
samsung_mdc/exceptions.py
samsung_mdc/fields.py
samsung_mdc/utils.py
samsung_mdc/version.py
python_samsung_mdc-1.17.0.dist-info/LICENSE
python_samsung_mdc-1.17.0.dist-info/METADATA
python_samsung_mdc-1.17.0.dist-info/WHEEL
python_samsung_mdc-1.17.0.dist-info/entry_points.txt
python_samsung_mdc-1.17.0.dist-info/top_level.txt
python_samsung_mdc-1.17.0.dist-info/RECORD
