Metadata-Version: 2.1
Name: python-samsung-mdc
Version: 1.17.0
Summary: Samsung Multiple Display Control (MDC) protocol implementation (asyncio library + CLI interface)
Home-page: http://github.com/vgavro/samsung-mdc
Author: Victor Gavro
Author-email: vgavro@gmail.com
License: BSD-3-Clause
Keywords: samsung,mdc
Classifier: License :: OSI Approved :: BSD License
Classifier: Intended Audience :: Developers
Classifier: Intended Audience :: System Administrators
Classifier: Intended Audience :: Telecommunications Industry
Classifier: Programming Language :: Python
Classifier: Programming Language :: Python :: 3
Classifier: Development Status :: 5 - Production/Stable
Classifier: Operating System :: OS Independent
Classifier: Topic :: Multimedia :: Video :: Display
Classifier: Topic :: Home Automation
Classifier: Topic :: Utilities
Requires-Python: >=3.7,<4.0
License-File: LICENSE
Requires-Dist: click
Requires-Dist: jinja2
Requires-Dist: pyserial-asyncio
Provides-Extra: all
Requires-Dist: pyserial-asyncio; extra == "all"
Provides-Extra: serial
Requires-Dist: pyserial-asyncio; extra == "serial"
Provides-Extra: test
Requires-Dist: pytest; extra == "test"
Requires-Dist: pytest-asyncio; extra == "test"
Requires-Dist: nest-asyncio; extra == "test"
